{
  "/src": {
    "percentage": null,
    "totalStatements": null,
    "coveredStatements": null
  },
  "/": {
    "percentage": null,
    "totalStatements": null,
    "coveredStatements": null
  },
  "/src/index.ts": {
    "percentage": null,
    "totalStatements": null,
    "coveredStatements": null,
    "testables": []
  },
  "/src/config": {
    "percentage": null,
    "totalStatements": null,
    "coveredStatements": null
  },
  "/src/config/db.ts": {
    "percentage": null,
    "totalStatements": null,
    "coveredStatements": null,
    "testables": [
      {
        "name": "connectDB",
        "percentage": null,
        "totalStatements": null,
        "coveredStatements": null
      },
      {
        "name": "connectDB",
        "percentage": null,
        "totalStatements": null,
        "coveredStatements": null
      }
    ]
  },
  "/src/config/env.ts": {
    "percentage": null,
    "totalStatements": null,
    "coveredStatements": null,
    "testables": []
  },
  "/src/controllers": {
    "percentage": null,
    "totalStatements": null,
    "coveredStatements": null
  },
  "/src/controllers/authController.ts": {
    "percentage": null,
    "totalStatements": null,
    "coveredStatements": null,
    "testables": [
      {
        "name": "login",
        "percentage": null,
        "totalStatements": null,
        "coveredStatements": null
      },
      {
        "name": "getProfile",
        "percentage": null,
        "totalStatements": null,
        "coveredStatements": null
      },
      {
        "name": "register",
        "percentage": null,
        "totalStatements": null,
        "coveredStatements": null
      },
      {
        "name": "logout",
        "percentage": null,
        "totalStatements": null,
        "coveredStatements": null
      }
    ]
  },
  "/src/controllers/paymentController.ts": {
    "percentage": null,
    "totalStatements": null,
    "coveredStatements": null,
    "testables": [
      {
        "name": "getAllPayments",
        "percentage": null,
        "totalStatements": null,
        "coveredStatements": null
      },
      {
        "name": "getPaymentsByStudent",
        "percentage": null,
        "totalStatements": null,
        "coveredStatements": null
      },
      {
        "name": "createPayment",
        "percentage": null,
        "totalStatements": null,
        "coveredStatements": null
      },
      {
        "name": "updatePayment",
        "percentage": null,
        "totalStatements": null,
        "coveredStatements": null
      },
      {
        "name": "getPaymentSummary",
        "percentage": null,
        "totalStatements": null,
        "coveredStatements": null
      }
    ]
  },
  "/src/controllers/serviceController.ts": {
    "percentage": null,
    "totalStatements": null,
    "coveredStatements": null,
    "testables": [
      {
        "name": "getServicesByStudent",
        "percentage": null,
        "totalStatements": null,
        "coveredStatements": null
      },
      {
        "name": "getServiceById",
        "percentage": null,
        "totalStatements": null,
        "coveredStatements": null
      },
      {
        "name": "createService",
        "percentage": null,
        "totalStatements": null,
        "coveredStatements": null
      },
      {
        "name": "updateService",
        "percentage": null,
        "totalStatements": null,
        "coveredStatements": null
      },
      {
        "name": "addSession",
        "percentage": null,
        "totalStatements": null,
        "coveredStatements": null
      }
    ]
  },
  "/src/controllers/studentController.ts": {
    "percentage": null,
    "totalStatements": null,
    "coveredStatements": null,
    "testables": [
      {
        "name": "getStudents",
        "percentage": null,
        "totalStatements": null,
        "coveredStatements": null
      },
      {
        "name": "getStudentById",
        "percentage": null,
        "totalStatements": null,
        "coveredStatements": null
      },
      {
        "name": "createStudent",
        "percentage": null,
        "totalStatements": null,
        "coveredStatements": null
      },
      {
        "name": "updateStudent",
        "percentage": null,
        "totalStatements": null,
        "coveredStatements": null
      },
      {
        "name": "deleteStudent",
        "percentage": null,
        "totalStatements": null,
        "coveredStatements": null
      }
    ]
  },
  "/src/middleware": {
    "percentage": null,
    "totalStatements": null,
    "coveredStatements": null
  },
  "/src/middleware/authMiddleware.ts": {
    "percentage": null,
    "totalStatements": null,
    "coveredStatements": null,
    "testables": [
      {
        "name": "protect",
        "percentage": null,
        "totalStatements": null,
        "coveredStatements": null
      },
      {
        "name": "superAdminOnly",
        "percentage": null,
        "totalStatements": null,
        "coveredStatements": null
      }
    ]
  },
  "/src/middleware/errorMiddleware.ts": {
    "percentage": null,
    "totalStatements": null,
    "coveredStatements": null,
    "testables": [
      {
        "name": "notFound",
        "percentage": null,
        "totalStatements": null,
        "coveredStatements": null
      },
      {
        "name": "globalErrorHandler",
        "percentage": null,
        "totalStatements": null,
        "coveredStatements": null
      }
    ]
  },
  "/src/middleware/validateMiddleware.ts": {
    "percentage": null,
    "totalStatements": null,
    "coveredStatements": null,
    "testables": [
      {
        "name": "validate",
        "percentage": null,
        "totalStatements": null,
        "coveredStatements": null
      }
    ]
  },
  "/src/routes": {
    "percentage": null,
    "totalStatements": null,
    "coveredStatements": null
  },
  "/src/routes/authRoutes.ts": {
    "percentage": null,
    "totalStatements": null,
    "coveredStatements": null,
    "testables": []
  },
  "/src/routes/paymentRoutes.ts": {
    "percentage": null,
    "totalStatements": null,
    "coveredStatements": null,
    "testables": []
  },
  "/src/routes/serviceRoutes.ts": {
    "percentage": null,
    "totalStatements": null,
    "coveredStatements": null,
    "testables": []
  },
  "/src/routes/studentRoutes.ts": {
    "percentage": null,
    "totalStatements": null,
    "coveredStatements": null,
    "testables": []
  },
  "/src/models": {
    "percentage": null,
    "totalStatements": null,
    "coveredStatements": null
  },
  "/src/models/Admin.ts": {
    "percentage": null,
    "totalStatements": null,
    "coveredStatements": null,
    "testables": [
      {
        "name": "comparePassword",
        "percentage": null,
        "totalStatements": null,
        "coveredStatements": null
      }
    ]
  },
  "/src/models/Payment.ts": {
    "percentage": null,
    "totalStatements": null,
    "coveredStatements": null,
    "testables": []
  },
  "/src/models/Service.ts": {
    "percentage": null,
    "totalStatements": null,
    "coveredStatements": null,
    "testables": []
  },
  "/src/models/Student.ts": {
    "percentage": null,
    "totalStatements": null,
    "coveredStatements": null,
    "testables": []
  },
  "/src/types": {
    "percentage": null,
    "totalStatements": null,
    "coveredStatements": null
  },
  "/src/types/index.ts": {
    "percentage": null,
    "totalStatements": null,
    "coveredStatements": null,
    "testables": []
  },
  "/src/utils": {
    "percentage": null,
    "totalStatements": null,
    "coveredStatements": null
  },
  "/src/utils/apiResponse.ts": {
    "percentage": null,
    "totalStatements": null,
    "coveredStatements": null,
    "testables": [
      {
        "name": "sendSuccess",
        "percentage": null,
        "totalStatements": null,
        "coveredStatements": null
      },
      {
        "name": "sendError",
        "percentage": null,
        "totalStatements": null,
        "coveredStatements": null
      },
      {
        "name": "sendPaginated",
        "percentage": null,
        "totalStatements": null,
        "coveredStatements": null
      }
    ]
  },
  "/src/utils/jwtHelper.ts": {
    "percentage": null,
    "totalStatements": null,
    "coveredStatements": null,
    "testables": [
      {
        "name": "generateToken",
        "percentage": null,
        "totalStatements": null,
        "coveredStatements": null
      },
      {
        "name": "verifyToken",
        "percentage": null,
        "totalStatements": null,
        "coveredStatements": null
      }
    ]
  }
}